{
  "ORDER": "TGM-64052",
  "KEYWORD": "TGM-64052 4I6D1R 8I4D1R 4I2D2R 2AP_420 HM-005-00 RS485 slave RM-012-IP",
  "DISPLAY": {
    "TYPE": "7 Segment / 7 Segment",
    "SIZE": "4\" / 8\"",
    "OTHER": " / "
  },
  "INPUT": {
    "TYPE": "Analog 4-20mA",
    "OTHER": "HM-005-00",
    "CHANNEL": "2"
  },
  "OUTPUT": {
    "TYPE": "Relay Alarm",
    "OTHER": "",
    "CHANNEL": "2"
  },
  "COMMUNICATION": {
    "TYPE": "RS485 MB RTU Slave",
    "OTHER": "RM-012-IP-485",
    "CHANNEL": ""
  },
  "SUPPLY": {
    "TYPE": "110-240 VAC/ 50-60Hz",
    "OTHER": ""
  },
  "SOURCES": {
    "TYPE": "-",
    "OTHER": ""
  },
  "FUNCTION": [
    "FUNCTION",
    "- ตั้งค่าการทำงานของ Alarm 2 channel ได้ 4 Mode",
    "    Alarm 1 ใช้งานกับ TEMP",
    "    Alarm 2 ใช้งานกับ HUMI",
    "- ตั้งค่า Slave Address ได้ 1 – 240",
    "- ตั้งค่า Baudrate ได้ 4800 9600 19200 38400 57600",
    "- ตั้งค่า Parity ได้ None Odd Even",
    "FEATURE",
    "- แสดงผล ค่าที่รับได้จาก HM-005-00 ได้ 0 – 99",
    "- แสดงผลเวลาและวันที่ ปัจจุบัน (RTC ภายใน)",
    "**(สามารถเลือกให้แสดงเวลาและวันที่ ที่รับจาก Modbus)",
    "- Output 1 ทำงานเมื่อมีการ On/Off ผ่าน Modbus RTU",
    "- Output 2 ทำงานเมื่อ Alarm 1 หรือ Alarm 2 เกิด Alarm",
    "- Mode Alarm ใช้งานได้ 4 Mode",
    "    Alarm high low",
    "    Alarm high",
    "    Alarm low",
    "    Alarm high low range",
    "- สามารถอ่านข้อมูลได้ Function 03h และ 04h",
    "- สามารถเขียนข้อมูลได้ Function 06h และ 10h"
  ],
  "BODYSIZE": "1100W x 600H x 100D",
  "DATE": "2021-03-16",
  "SALE": {
    "NAME": "คุณ นิติพนธิ์ มณีรุ่ง",
    "BRANCH": "ชลบุรี",
    "CALL": "0908808243",
    "EMAIL": "",
    "CUSTOMER": ""
  }
}